SegSRGAN/Function_for_application_test_python3.py
SegSRGAN/SegSRGAN_training.py
SegSRGAN/__init__.py
SegSRGAN/job_model.py
SegSRGAN/job epirmex/Job.py
SegSRGAN/job epirmex/__init__.py
SegSRGAN/utils/Adam_lr_mult.py
SegSRGAN/utils/ImageReader.py
SegSRGAN/utils/SegSRGAN.py
SegSRGAN/utils/__init__.py
SegSRGAN/utils/download.py
SegSRGAN/utils/interpolation.py
SegSRGAN/utils/layers.py
SegSRGAN/utils/normalization.py
SegSRGAN/utils/patches.py
SegSRGAN/utils/utils3d.py
SegSRGAN-2.2.4.dist-info/LICENSE.md
SegSRGAN-2.2.4.dist-info/METADATA
SegSRGAN-2.2.4.dist-info/WHEEL
SegSRGAN-2.2.4.dist-info/top_level.txt
SegSRGAN-2.2.4.dist-info/RECORD
