Metadata-Version: 2.1
Name: SegSRGAN
Version: 2.2.4
Summary: Segmentation and super resolution GAN network
Home-page: https://github.com/koopa31/SegSRGAN
Author: Clément Cazorla
Author-email: clement.cazorla@univ-reims.fr
License: UNKNOWN
Platform: UNKNOWN
Requires-Dist: numpy (==1.16.2)
Requires-Dist: SimpleITK (==1.2.0)
Requires-Dist: scipy (==1.2.0)
Requires-Dist: tensorflow (==1.13.1)
Requires-Dist: keras (==2.2.4)
Requires-Dist: pandas (==0.23.0)
Requires-Dist: progressbar2 (==3.39.2)
Requires-Dist: requests (==2.18.4)
Requires-Dist: wget (==3.2)
Requires-Dist: sklearn (==0.0)
